narlivs/Base.py
narlivs/Client.py
narlivs/MainClass.py
narlivs/Product.py
narlivs/__init__.py
pynarlivs-0.9.0.dist-info/DESCRIPTION.rst
pynarlivs-0.9.0.dist-info/METADATA
pynarlivs-0.9.0.dist-info/RECORD
pynarlivs-0.9.0.dist-info/WHEEL
pynarlivs-0.9.0.dist-info/metadata.json
pynarlivs-0.9.0.dist-info/top_level.txt
