Metadata-Version: 2.0
Name: pynarlivs
Version: 0.9.0
Summary: Client library for the non-existent Narlivs API.
Home-page: https://github.com/uppsaladatavetare/pynarlivs
Author: Krzysztof Jagiello
Author-email: me@kjagiello.com
License: MIT license
Platform: UNKNOWN
Requires-Dist: lxml (==3.6.4)
Requires-Dist: robobrowser (==0.5.3)
